Metadata-Version: 2.1
Name: lyywmdf
Version: 1.18
Summary: userfull application for  lyy
Author: lyy
Author-email: 
License: MIT
License-File: LICENSE
Requires-Dist: pandas
Requires-Dist: tqdm
Requires-Dist: MyTT
Requires-Dist: numpy
